brunhilda/__init__.py
brunhilda/brunhilda.py
brunhilda/data.py
brunhilda/exception.py
brunhilda/html_feature_summary_output.py
brunhilda/html_index_output.py
brunhilda/html_issue_list_output.py
brunhilda/html_output.py
brunhilda/html_req_summary_output.py
brunhilda/html_result_output.py
brunhilda/html_test_plan_output.py
brunhilda/html_test_summary_output.py
brunhilda/html_trace_output.py
brunhilda/html_user_stories_summary.py
brunhilda/junit_result_output.py
brunhilda/loader.py
brunhilda/output.py
brunhilda/parser.py
brunhilda/rel_path.py
brunhilda/reporter.py
brunhilda/result.py
brunhilda/tag_filter.py
brunhilda/templates/header.html.jinja2
brunhilda/templates/index.html.jinja2
brunhilda/templates/issue-list.html.jinja2
brunhilda/templates/summary-features.html.jinja2
brunhilda/templates/summary-req.html.jinja2
brunhilda/templates/summary-test.html.jinja2
brunhilda/templates/summary-user-stories.html.jinja2
brunhilda/templates/summary.html.jinja2
brunhilda/templates/template.html.jinja2
brunhilda/templates/template.junit.jinja2
brunhilda/templates/test-plan.html.jinja2
brunhilda/templates/trace.html.jinja2
brunhilda/templates/themes/base.css
brunhilda/tests/__init__.py
brunhilda/tests/test_tag_filter.py
brunhilda-2.4.0.dist-info/LICENSE
brunhilda-2.4.0.dist-info/METADATA
brunhilda-2.4.0.dist-info/WHEEL
brunhilda-2.4.0.dist-info/top_level.txt
brunhilda-2.4.0.dist-info/RECORD
