Metadata-Version: 2.1
Name: brunhilda
Version: 2.4.0
Summary: Bender Robotics System Test Runner
Home-page: https://www.benderrobotics.com
Author: Bender Robotics
Author-email: kumpan@benderrobotics.com
License: UNKNOWN
Platform: UNKNOWN
Classifier: Programming Language :: Python :: 3
Classifier: License :: OSI Approved :: MIT License
Classifier: Operating System :: OS Independent
Classifier: Programming Language :: Python
Classifier: Programming Language :: Python :: 3
Classifier: Programming Language :: Python :: 3.7
Classifier: Programming Language :: Python :: 3.8
Classifier: Programming Language :: Python :: 3.9
Classifier: Programming Language :: Python :: 3.10
Classifier: Programming Language :: Python :: 3.11
Requires-Python: >=3.7
License-File: LICENSE
Requires-Dist: Jinja2>=2.10.3
Requires-Dist: numpy<1.24,>=1.17.3
Requires-Dist: ddt>=1.2.2
Requires-Dist: colorama>=0.4.1
Requires-Dist: docutils>=0.15.2
Requires-Dist: Pillow>=7.2.0
Requires-Dist: pyyaml
Requires-Dist: simplejson>=3.17.6
Requires-Dist: doorstop==2.2.post1
Requires-Dist: natsort>=8.1.0
